{
    "Institution": "Zoologisches Institut und zoologische Sammlung",
    "Year": 1914,
    "Page_Begin": 125,
    "Page_End": 130,
    "Text": "====PAGEBEGIN 125====\r\n\r\n191\r\nDie Zahl der im Institut arbeitenden Professoren, Assi­stenten und Doktoranden betrug im S.-S. 22, im W.-S. 10.\r\nVon den Assistenten des Institutes ist zurzeit Dr. Pohl\r\nals wissenschaftlicher Mitarbeiter der Verkehrstechnischen\r\nPrüfungskommission tätig. Im Felde stehen: die Herren\r\nDr. Westphal, Dr. Hertz und Dr. Franck als Leut­nants der Reserve, Professor von Baeyer als Offizierstell­vertreter, Dr. Liebreich als Feldintendanturassessor, Dr.\r\nPringsheim ist seit Kriegsbeginn Kriegsgefangener in\r\nAustralien. |\r\nFerner sind zum Militärdienst eingezogen: der Hausver­walter Hıllmann als Vizefeldwebel, der Mechaniker\r\nPaetzold als Unteroffizier, der Hilfsdiener Andree als\r\nKraftwagenführer und der Hilfsdiener Ha gen zur Infanterie.\r\nDer Direktor des physikalischen Instituts:\r\nRubens.\r\n42. Das Institut für theoretische Physik.\r\n(C. 2, Universitätsgebäude.)\r\nIm Anschluß an die Vorlesungen, deren Besuchsziffer im\r\nSommer 171, im Winter 83 betrug, wurden, wie bisher, in\r\njedem Semester mathematisch-physikalische Übungen abge­halten, in welehen allwöchentlich schriftliche Arbeiten über\r\nbestimmte, den vorgetragenen Theorien entnommene Themata\r\naufgegeben und besprochen wurden. Die Zahl der an den\r\nÜbungen mit Erfolg teilnehmenden Studierenden betrug im\r\n5.8. 72, darunter 9 Frauen, im W.-S. 96, darunter 6 Frauen.\r\nM. Planek.\r\n43. Das zoologische Institut.\r\n(N. 4, Invalidenstr. 43.)\r\nZum Heeresdienst wurden eingezogen: der zweite Assistent\r\nDr. Schulze , der Präparator Baroke und der Hilfsdiener\r\nLutz.\r\nAnderungen im Beamtenstand kamen nicht vor.\r\nEs wurden erworben: Einriehtungsgegen­stinde: 4 Kursmikroskope, 4 Mikrotome nach Schanze­Altmann; Bücher: 56 neue Werke, 91 laufende Bände von\r\nZeitschriften und . Lieferungswerken; 6 Wandtafeln:\r\n\r\n====PAGEBREAK TO 126====\r\n\r\n-- 1 ­18 Nummern Studienmaterlal; 57 Demonstra­tionspräparate..\r\nDie Teilnehmerzahl der Kurse und Praktika betrug:\r\nIm Sommerhalbjahre:\r\nMakroskopisch-zootomischer Kurs: 62 Herren, 3 Damen.\r\nMikroskopisch-zoologiseher Kurs, II. Teil: 7 Herren, 2 Damen.\r\nWissenschaftliche Arbeiten im Institut: 9 Herren, 2 Damen.\r\nIm Winterhalbjahre:\r\nMikroskopisch-zoologischer Kurs, I. Teil: 6 Herren, 1 Dame.\r\nWissenschaftliehe Arbeiten im Institut: 9 Herren, 4 Damen.\r\nFolgende wichtige Publikationen gingen aus dem Institut\r\nhervor:\r\nSchulze, ¥. E.: Kritik neuerer Mitteilungen über Trichoplax.\r\nZoologischer Anzeiger. XLIV. 1.\r\nBericht über das „Tierreich“. Sitzungsber. d. Kel. Akad. d.\r\nWissensch. VI, 1915.\r\nHerausgabe des , Tierreich“. Lfg. 41: Kieffer, J. J.: Bethy­lidae; Lfg. 42: Kieffer, J. J.: Serphidae et Calliceratidae.\r\nQuiel, G.: Untersuchungen an Collembolen. Inaug.- Diss.\r\nKremer, J.: Zur Histologie der Coleoptera. Inaug.- Diss.\r\nAußerdem wurden 9 kleinere Arbeiten und vorläufige Mit­teilungen publiziert.\r\nDer Direktor:\r\nProf. F. E. Sehulze.\r\n44. Das mineralogiseh-petrographische Institut und Museum.\r\n(N. 4, Invalidenstr. 43.)\r\nI Personalien.\r\nAn Stelle des Hilfsdieners Arno Mende trat am 1. Aug.\r\nder Militäranwürter Gustav Schreiber aus Kittlitztreben\r\nzur probeweisen Dienstleistung ein; er wurde am 1. März aw\r\ngestellt.\r\nDie Assistenten Dr. Ernst Korreng und Dr. Erhard\r\nVortisceh sowie der wissenschaftliche Hilfsarbeiter Dr. Otto\r\nGall wurden zu den Fahnen einberufen.\r\nDem Kustos und Privatdozenten Prof. Dr. Max Be­lowsky wurde der Rote Adlerorden IV. Klasse verliehen.\r\n195\r\n\r\n====PAGEBREAK TO 129====\r\n\r\n46. Das zoologische Museum.*)\r\n(N. 4, Invalidenstr. 43.)\r\nDer Krieg hatte naturgemäß auch einen großen Einfluß\r\nauf die Arbeiten des Museums. Da 8 Beamte und Hilfsarbeiter\r\nzum Heere eingezogen waren, konnten viele Aufgaben in der\r\nSchau- und Hauptsammlung nicht durchgeführt werden. Die\r\nZahl der Eingänge, der Verkehr mit dem Ausland und die hie­sige Benutzung der Sammlungen war während des Krieges\r\ngering. Dagegen war es möglich, die Ordnung und Bearbeitung\r\nfrüherer Eingänge stärker zu fördern als sonst. Als ein Ereig­nis von größter Wichtigkeit für die Entwicklung des Museums\r\nmuß der Beginn des schon lange erstrebten Anbaus verzeichnet\r\nwerden, der dem drückenden Platzmangel für lange Zeit Ab­hilfe schaffen wird.\r\n1. Personalien.\r\nDer Assistent Dr. Aulmann schied am 1. April 1914\r\ninfolge seiner Ernennung zum Direktor des Löbbecke-Museums\r\nder Stadt Düsseldorf aus; sein Nachfolger wurde der bisherize\r\nwissensehaftliehe Hilfsarbeiter Dr. Bisehoff,und an seine\r\nStelle trat Dr. Stobbe. Der Präparator Burger verlief\r\ndas Museum am 1. Oktober, um eine bessere Stellung am Natur­historischen Museum in Wiesbaden zu übernehmen. Die Stelle\r\ndes Hilfsdieners Kaschke, der am 1. September austrat, er­hielt Burzlaff.\r\nAm 17. Februar 1915 starb der Konservator G. Krause.\r\n2. Bibliothek.\r\nDer Zuwachs betrug rund 1240 Bände; eine große Zahl\r\nwurde von der Gesellschaft naturforschender Freunde in Berlin\r\nund von mehreren wissenschaftlichen Beamten des Museums\r\ngeschenkt und weiter fiel dem Museum als Vermächtnis die\r\nentomologische Bibliothek des verstorbenen Rechnungsrats a. D.\r\nG. Weymer in Elberfeld zu. In Schriftenaustausch steht das\r\nMuseum mit 194 wissenschaftlichen Anstalten.\r\n3. Sehau- und Hauptsammlun g.\r\nIn der Schausammlung wurden 20 Tiere und 50 anato­mische Präparate neu aufgestellt. Die Hauptsammlung ver­*) Der ausführliche Bericht erscheint in den ,Mitteilungen des Zoolo­gischen Museums, 8. Bd. 1. H. 1915.*\r\n195 .\r\n\r\n====PAGEBREAK TO 130====\r\n\r\nmehrte sich um rund 5000 Wirbeltiere und um mehr als 80 000\r\nwirbellose Tiere, besonders Insekten. Durch das Testament des\r\nverstorbenen Rechnungsrats a. D. G. Weymer in Elberfeld\r\nerhielt das Museum seine Schmetterlingssammlung, welche\r\ndurch den großen Umfang (ca. 36000 Stück, etwa 10 000\r\nArten aus allen Erdteilen) und besonders durch die große Zahl\r\nvon Typen eine sehr wertvolle Bereicherung des Museums\r\nbedeutet.\r\nDie Sammlungen wurden in rund 900 Fällen von hiesigen\r\nund auswärtigen Forschern und Instituten in Anspruch ge­nommen.\r\n4. Veröffentlichungen.\r\nVom, Museum wurden veröffentlicht: 1. Mitteilungen aus\r\ndem Zoologischen Museum, Bd. VII, H. 2 und 3; 2. l'auna der\r\ndeutschen Kolonien, Reihe 6, H. 1.\r\nVon Beamten und Forschern, die im Museum arbeiteten,\r\nwurden 78 Arbeiten veröffentlicht. A. Brauer.\r\n41. Die allgemeine Verwaltung des Museums für Naturkunde.\r\n(N. 4, Invalidenstr. 43.)\r\nDie Schausammlung wurde im Rechnungsjahr 1914 von\r\n48 723 Personen und 172 Schulklassen besucht. Es ergibt sich\r\ndanach ein geringerer Besuch von 43 913 Personen und 160\r\nSchulklassen, dessen Ursache wohl ausschließlich im Kriege zu\r\nsuchen ist. Aus diesem Grunde ist auch die Veranstaltung von\r\nFührungen und Vortrügen im Winterhalbjahr 1914/15 unter\r\nblieben.\r\nDie Besuchszeit wurde der sehwücheren Benutzung ent­sprechend vom September 1914 ab Sonntags von 12 bis 4 Uhr\r\nund an den in Frage kommenden Wochentagen von 11 bis 2 Uhr\r\nfestgesetzt.\r\nVersetzt wurde am 1. Mai 1914 der DBureauassistent\r\nScharowsky in gleicher Eigenschaft an das Hygienische\r\nInstitut und der Bureauassistent Schulz vom Königlichen\r\nKlinikum zum Museum. Der Maschinist Weinberg wurde\r\nnach beendeter Probedienstzeit am 1. April 1914 angestellt. Am\r\n3. Oktober erfolgte die Einberufung des Sekretärs Wahmke\r\nzum Heeresdienst.\r\nMit dem  Erweiterungsbau des Museums wurde am\r\n126",
    "Entities": {
        "58781": {
            "id": "58781",
            "type": "E54 Dimension",
            "short_type": "E54",
            "virtual": false,
            "text": "80 000",
            "search_string": "80000",
            "begin": 5482,
            "end": 5488,
            "page": 130,
            "original_page": 0,
            "url": "",
            "citation": "",
            "line": 1,
            "txt_id": "Zoo_1914",
            "line_idx": 126,
            "institution": "Zoologisches Institut und zoologische Sammlung",
            "year": 1914,
            "mentions": 1,
            "color": "#50c4c2aa",
            "incoming": [
                "72813"
            ],
            "outgoing": []
        },
        "58782": {
            "id": "58782",
            "type": "E28 Conceptual Object",
            "short_type": "E28",
            "virtual": false,
            "text": "wirbellose Tiere",
            "search_string": "wirbellosetiere",
            "begin": 5490,
            "end": 5506,
            "page": 130,
            "original_page": 0,
            "url": "",
            "citation": "",
            "line": 2,
            "txt_id": "Zoo_1914",
            "line_idx": 127,
            "institution": "Zoologisches Institut und zoologische Sammlung",
            "year": 1914,
            "mentions": 1,
            "color": "#06b67eaa",
            "incoming": [
                "72814"
            ],
            "outgoing": [
                "72793"
            ]
        },
        "58784": {
            "id": "58784",
            "type": "E20 Biological Object",
            "short_type": "E20",
            "virtual": false,
            "text": "Tiere",
            "search_string": "tiere",
            "begin": 5501,
            "end": 5506,
            "page": 130,
            "original_page": 0,
            "url": "",
            "citation": "",
            "line": 2,
            "txt_id": "Zoo_1914",
            "line_idx": 127,
            "institution": "Zoologisches Institut und zoologische Sammlung",
            "year": 1914,
            "mentions": 1,
            "color": "#5a50c4aa",
            "incoming": [
                "72815"
            ],
            "outgoing": [
                "72813",
                "72814",
                "72816"
            ]
        },
        "58785": {
            "id": "58785",
            "type": "E28 Conceptual Object",
            "short_type": "E28",
            "virtual": false,
            "text": "Insekten",
            "search_string": "insekten",
            "begin": 5518,
            "end": 5526,
            "page": 130,
            "original_page": 0,
            "url": "",
            "citation": "",
            "line": 2,
            "txt_id": "Zoo_1914",
            "line_idx": 127,
            "institution": "Zoologisches Institut und zoologische Sammlung",
            "year": 1914,
            "mentions": 1,
            "color": "#06b67eaa",
            "incoming": [
                "72816"
            ],
            "outgoing": [
                "72794"
            ]
        },
        "58787": {
            "id": "58787",
            "type": "E3 Condition State",
            "short_type": "E3",
            "virtual": false,
            "text": "verstorben",
            "search_string": "verstorben",
            "begin": 5553,
            "end": 5563,
            "page": 130,
            "original_page": 0,
            "url": "",
            "citation": "",
            "line": 3,
            "txt_id": "Zoo_1914",
            "line_idx": 128,
            "institution": "Zoologisches Institut und zoologische Sammlung",
            "year": 1914,
            "mentions": 1,
            "color": "#50c4c2aa",
            "incoming": [
                "72817"
            ],
            "outgoing": []
        },
        "58790": {
            "id": "58790",
            "type": "E8 Acquisition",
            "short_type": "E8",
            "virtual": false,
            "text": "erhielt",
            "search_string": "erhielt",
            "begin": 5610,
            "end": 5617,
            "page": 130,
            "original_page": 0,
            "url": "",
            "citation": "",
            "line": 4,
            "txt_id": "Zoo_1914",
            "line_idx": 129,
            "institution": "Zoologisches Institut und zoologische Sammlung",
            "year": 1914,
            "mentions": 1,
            "color": "#fc3915aa",
            "incoming": [],
            "outgoing": [
                "72797",
                "72818",
                "72822",
                "72830"
            ]
        },
        "58791": {
            "id": "58791",
            "type": "E28 Conceptual Object",
            "short_type": "E28",
            "virtual": false,
            "text": "Schmetterlings",
            "search_string": "schmetterlings",
            "begin": 5635,
            "end": 5649,
            "page": 130,
            "original_page": 0,
            "url": "",
            "citation": "",
            "line": 4,
            "txt_id": "Zoo_1914",
            "line_idx": 129,
            "institution": "Zoologisches Institut und zoologische Sammlung",
            "year": 1914,
            "mentions": 1,
            "color": "#06b67eaa",
            "incoming": [
                "72820"
            ],
            "outgoing": [
                "72795"
            ]
        },
        "58793": {
            "id": "58793",
            "type": "E54 Dimension",
            "short_type": "E54",
            "virtual": false,
            "text": "36000",
            "search_string": "36000",
            "begin": 5696,
            "end": 5701,
            "page": 130,
            "original_page": 0,
            "url": "",
            "citation": "",
            "line": 5,
            "txt_id": "Zoo_1914",
            "line_idx": 130,
            "institution": "Zoologisches Institut und zoologische Sammlung",
            "year": 1914,
            "mentions": 1,
            "color": "#50c4c2aa",
            "incoming": [
                "72821"
            ],
            "outgoing": []
        },
        "58794": {
            "id": "58794",
            "type": "E19 Physical Object",
            "short_type": "E19",
            "virtual": false,
            "text": "Stück",
            "search_string": "stück",
            "begin": 5702,
            "end": 5707,
            "page": 130,
            "original_page": 0,
            "url": "",
            "citation": "",
            "line": 5,
            "txt_id": "Zoo_1914",
            "line_idx": 130,
            "institution": "Zoologisches Institut und zoologische Sammlung",
            "year": 1914,
            "mentions": 1,
            "color": "#5a50c4aa",
            "incoming": [
                "72822"
            ],
            "outgoing": [
                "72820",
                "72821",
                "72824",
                "72825"
            ]
        },
        "58762": {
            "id": "58762",
            "type": "E78 Curated Holding",
            "short_type": "E78",
            "virtual": false,
            "text": "Hauptsammlung",
            "search_string": "hauptsammlung",
            "begin": 3692,
            "end": 3705,
            "page": 129,
            "original_page": 0,
            "url": "",
            "citation": "",
            "line": 6,
            "txt_id": "Zoo_1914",
            "line_idx": 89,
            "institution": "Zoologisches Institut und zoologische Sammlung",
            "year": 1914,
            "mentions": 1,
            "color": "#b560d4aa",
            "incoming": [
                "72796",
                "72797",
                "72798"
            ],
            "outgoing": []
        },
        "58795": {
            "id": "58795",
            "type": "E54 Dimension",
            "short_type": "E54",
            "virtual": false,
            "text": "10 000",
            "search_string": "10000",
            "begin": 5714,
            "end": 5720,
            "page": 130,
            "original_page": 0,
            "url": "",
            "citation": "",
            "line": 5,
            "txt_id": "Zoo_1914",
            "line_idx": 130,
            "institution": "Zoologisches Institut und zoologische Sammlung",
            "year": 1914,
            "mentions": 1,
            "color": "#50c4c2aa",
            "incoming": [
                "72823"
            ],
            "outgoing": []
        },
        "58796": {
            "id": "58796",
            "type": "E28 Conceptual Object",
            "short_type": "E28",
            "virtual": false,
            "text": "Arten",
            "search_string": "arten",
            "begin": 5722,
            "end": 5727,
            "page": 130,
            "original_page": 0,
            "url": "",
            "citation": "",
            "line": 6,
            "txt_id": "Zoo_1914",
            "line_idx": 131,
            "institution": "Zoologisches Institut und zoologische Sammlung",
            "year": 1914,
            "mentions": 1,
            "color": "#06b67eaa",
            "incoming": [
                "72824"
            ],
            "outgoing": [
                "72823",
                "72831"
            ]
        },
        "58797": {
            "id": "58797",
            "type": "E53 Place",
            "short_type": "E53",
            "virtual": false,
            "text": "allen Erdteilen",
            "search_string": "allenerdteilen",
            "begin": 5732,
            "end": 5747,
            "page": 130,
            "original_page": 0,
            "url": "",
            "citation": "",
            "line": 6,
            "txt_id": "Zoo_1914",
            "line_idx": 131,
            "institution": "Zoologisches Institut und zoologische Sammlung",
            "year": 1914,
            "mentions": 1,
            "color": "#fc7715aa",
            "incoming": [
                "72825"
            ],
            "outgoing": []
        },
        "58763": {
            "id": "58763",
            "type": "E8 Acquisition",
            "short_type": "E8",
            "virtual": false,
            "text": "Eingänge",
            "search_string": "eingänge",
            "begin": 3747,
            "end": 3755,
            "page": 129,
            "original_page": 0,
            "url": "",
            "citation": "",
            "line": 7,
            "txt_id": "Zoo_1914",
            "line_idx": 90,
            "institution": "Zoologisches Institut und zoologische Sammlung",
            "year": 1914,
            "mentions": 1,
            "color": "#fc3915aa",
            "incoming": [],
            "outgoing": [
                "72798",
                "72799",
                "72826"
            ]
        },
        "58764": {
            "id": "58764",
            "type": "E54 Dimension",
            "short_type": "E54",
            "virtual": false,
            "text": "gering",
            "search_string": "gering",
            "begin": 3852,
            "end": 3858,
            "page": 129,
            "original_page": 0,
            "url": "",
            "citation": "",
            "line": 9,
            "txt_id": "Zoo_1914",
            "line_idx": 92,
            "institution": "Zoologisches Institut und zoologische Sammlung",
            "year": 1914,
            "mentions": 1,
            "color": "#50c4c2aa",
            "incoming": [
                "72799"
            ],
            "outgoing": []
        },
        "58798": {
            "id": "58798",
            "type": "E55 Type",
            "short_type": "E55",
            "virtual": true,
            "text": "Gift",
            "search_string": "gift",
            "begin": null,
            "end": null,
            "page": -1,
            "original_page": 0,
            "url": "",
            "citation": "",
            "line": -1,
            "txt_id": "Zoo_1914",
            "line_idx": 0,
            "institution": "Zoologisches Institut und zoologische Sammlung",
            "year": 1914,
            "mentions": 1,
            "color": "#06b67eaa",
            "incoming": [
                "72826",
                "72827",
                "72828",
                "72829",
                "72830"
            ],
            "outgoing": []
        },
        "58765": {
            "id": "58765",
            "type": "E78 Curated Holding",
            "short_type": "E78",
            "virtual": false,
            "text": "Bibliothek",
            "search_string": "bibliothek",
            "begin": 4734,
            "end": 4744,
            "page": 129,
            "original_page": 0,
            "url": "",
            "citation": "",
            "line": 26,
            "txt_id": "Zoo_1914",
            "line_idx": 109,
            "institution": "Zoologisches Institut und zoologische Sammlung",
            "year": 1914,
            "mentions": 1,
            "color": "#b560d4aa",
            "incoming": [
                "72800",
                "72801"
            ],
            "outgoing": []
        },
        "58766": {
            "id": "58766",
            "type": "E8 Acquisition",
            "short_type": "E8",
            "virtual": false,
            "text": "Zuwachs",
            "search_string": "zuwachs",
            "begin": 4751,
            "end": 4758,
            "page": 129,
            "original_page": 0,
            "url": "",
            "citation": "",
            "line": 27,
            "txt_id": "Zoo_1914",
            "line_idx": 110,
            "institution": "Zoologisches Institut und zoologische Sammlung",
            "year": 1914,
            "mentions": 1,
            "color": "#fc3915aa",
            "incoming": [],
            "outgoing": [
                "72800",
                "72803",
                "72827"
            ]
        },
        "58767": {
            "id": "58767",
            "type": "E54 Dimension",
            "short_type": "E54",
            "virtual": false,
            "text": "1240",
            "search_string": "1240",
            "begin": 4771,
            "end": 4775,
            "page": 129,
            "original_page": 0,
            "url": "",
            "citation": "",
            "line": 27,
            "txt_id": "Zoo_1914",
            "line_idx": 110,
            "institution": "Zoologisches Institut und zoologische Sammlung",
            "year": 1914,
            "mentions": 1,
            "color": "#50c4c2aa",
            "incoming": [
                "72802"
            ],
            "outgoing": []
        },
        "58768": {
            "id": "58768",
            "type": "E19 Physical Object",
            "short_type": "E19",
            "virtual": false,
            "text": "Bände",
            "search_string": "bände",
            "begin": 4776,
            "end": 4781,
            "page": 129,
            "original_page": 0,
            "url": "",
            "citation": "",
            "line": 27,
            "txt_id": "Zoo_1914",
            "line_idx": 110,
            "institution": "Zoologisches Institut und zoologische Sammlung",
            "year": 1914,
            "mentions": 1,
            "color": "#5a50c4aa",
            "incoming": [
                "72803"
            ],
            "outgoing": [
                "72802"
            ]
        },
        "58769": {
            "id": "58769",
            "type": "E74 Group",
            "short_type": "E74",
            "virtual": false,
            "text": "Gesellschaft naturforschender Freunde in Berlin",
            "search_string": "gesellschaftnaturforschenderfreundeinberlin",
            "begin": 4814,
            "end": 4861,
            "page": 129,
            "original_page": 0,
            "url": "",
            "citation": "",
            "line": 28,
            "txt_id": "Zoo_1914",
            "line_idx": 111,
            "institution": "Zoologisches Institut und zoologische Sammlung",
            "year": 1914,
            "mentions": 1,
            "color": "#3b95c4aa",
            "incoming": [
                "72804"
            ],
            "outgoing": [
                "72805"
            ]
        },
        "58770": {
            "id": "58770",
            "type": "E53 Place",
            "short_type": "E53",
            "virtual": false,
            "text": "Berlin",
            "search_string": "berlin",
            "begin": 4855,
            "end": 4861,
            "page": 129,
            "original_page": 0,
            "url": "",
            "citation": "",
            "line": 28,
            "txt_id": "Zoo_1914",
            "line_idx": 111,
            "institution": "Zoologisches Institut und zoologische Sammlung",
            "year": 1914,
            "mentions": 1,
            "color": "#fc7715aa",
            "incoming": [
                "72805"
            ],
            "outgoing": []
        },
        "58771": {
            "id": "58771",
            "type": "E74 Group",
            "short_type": "E74",
            "virtual": false,
            "text": "wissenschaftlichen Beamten",
            "search_string": "wissenschaftlichenbeamten",
            "begin": 4880,
            "end": 4906,
            "page": 129,
            "original_page": 0,
            "url": "",
            "citation": "",
            "line": 29,
            "txt_id": "Zoo_1914",
            "line_idx": 112,
            "institution": "Zoologisches Institut und zoologische Sammlung",
            "year": 1914,
            "mentions": 1,
            "color": "#3b95c4aa",
            "incoming": [
                "72806"
            ],
            "outgoing": []
        },
        "58772": {
            "id": "58772",
            "type": "E8 Acquisition",
            "short_type": "E8",
            "virtual": false,
            "text": "geschenkt",
            "search_string": "geschenkt",
            "begin": 4920,
            "end": 4929,
            "page": 129,
            "original_page": 0,
            "url": "",
            "citation": "",
            "line": 30,
            "txt_id": "Zoo_1914",
            "line_idx": 113,
            "institution": "Zoologisches Institut und zoologische Sammlung",
            "year": 1914,
            "mentions": 1,
            "color": "#fc3915aa",
            "incoming": [],
            "outgoing": [
                "72801",
                "72804",
                "72806",
                "72808",
                "72828"
            ]
        },
        "58773": {
            "id": "58773",
            "type": "E3 Condition State",
            "short_type": "E3",
            "virtual": false,
            "text": "verstorben",
            "search_string": "verstorben",
            "begin": 5008,
            "end": 5018,
            "page": 129,
            "original_page": 0,
            "url": "",
            "citation": "",
            "line": 31,
            "txt_id": "Zoo_1914",
            "line_idx": 114,
            "institution": "Zoologisches Institut und zoologische Sammlung",
            "year": 1914,
            "mentions": 1,
            "color": "#50c4c2aa",
            "incoming": [
                "72807"
            ],
            "outgoing": []
        },
        "58774": {
            "id": "58774",
            "type": "E21 Person",
            "short_type": "E21",
            "virtual": false,
            "text": "Rechnungsrats a. D. G. Weymer",
            "search_string": "rechnungsratsa.d.g.weymer",
            "begin": 5021,
            "end": 5051,
            "page": 129,
            "original_page": 0,
            "url": "",
            "citation": "",
            "line": 31,
            "txt_id": "Zoo_1914",
            "line_idx": 114,
            "institution": "Zoologisches Institut und zoologische Sammlung",
            "year": 1914,
            "mentions": 2,
            "color": "#3b95c4aa",
            "incoming": [
                "72808",
                "72818"
            ],
            "outgoing": [
                "72807",
                "72809",
                "72817",
                "72819"
            ]
        },
        "58775": {
            "id": "58775",
            "type": "E53 Place",
            "short_type": "E53",
            "virtual": false,
            "text": "Elberfeld",
            "search_string": "elberfeld",
            "begin": 5055,
            "end": 5064,
            "page": 129,
            "original_page": 0,
            "url": "",
            "citation": "",
            "line": 32,
            "txt_id": "Zoo_1914",
            "line_idx": 115,
            "institution": "Zoologisches Institut und zoologische Sammlung",
            "year": 1914,
            "mentions": 2,
            "color": "#fc7715aa",
            "incoming": [
                "72809",
                "72819"
            ],
            "outgoing": []
        },
        "58776": {
            "id": "58776",
            "type": "E8 Acquisition",
            "short_type": "E8",
            "virtual": false,
            "text": "mehrte",
            "search_string": "mehrte",
            "begin": 5429,
            "end": 5435,
            "page": 130,
            "original_page": 0,
            "url": "",
            "citation": "",
            "line": 1,
            "txt_id": "Zoo_1914",
            "line_idx": 126,
            "institution": "Zoologisches Institut und zoologische Sammlung",
            "year": 1914,
            "mentions": 1,
            "color": "#fc3915aa",
            "incoming": [],
            "outgoing": [
                "72796",
                "72812",
                "72815",
                "72829"
            ]
        },
        "58777": {
            "id": "58777",
            "type": "E54 Dimension",
            "short_type": "E54",
            "virtual": false,
            "text": "5000",
            "search_string": "5000",
            "begin": 5449,
            "end": 5453,
            "page": 130,
            "original_page": 0,
            "url": "",
            "citation": "",
            "line": 1,
            "txt_id": "Zoo_1914",
            "line_idx": 126,
            "institution": "Zoologisches Institut und zoologische Sammlung",
            "year": 1914,
            "mentions": 1,
            "color": "#50c4c2aa",
            "incoming": [
                "72810"
            ],
            "outgoing": []
        },
        "58778": {
            "id": "58778",
            "type": "E28 Conceptual Object",
            "short_type": "E28",
            "virtual": false,
            "text": "Wirbeltiere",
            "search_string": "wirbeltiere",
            "begin": 5454,
            "end": 5465,
            "page": 130,
            "original_page": 0,
            "url": "",
            "citation": "",
            "line": 1,
            "txt_id": "Zoo_1914",
            "line_idx": 126,
            "institution": "Zoologisches Institut und zoologische Sammlung",
            "year": 1914,
            "mentions": 1,
            "color": "#06b67eaa",
            "incoming": [
                "72811"
            ],
            "outgoing": [
                "72792"
            ]
        },
        "58779": {
            "id": "58779",
            "type": "E55 Type",
            "short_type": "E55",
            "virtual": true,
            "text": "Taxon",
            "search_string": "taxon",
            "begin": null,
            "end": null,
            "page": -1,
            "original_page": 0,
            "url": "",
            "citation": "",
            "line": -1,
            "txt_id": "Zoo_1914",
            "line_idx": 0,
            "institution": "Zoologisches Institut und zoologische Sammlung",
            "year": 1914,
            "mentions": 5,
            "color": "#06b67eaa",
            "incoming": [
                "72792",
                "72793",
                "72794",
                "72795",
                "72831"
            ],
            "outgoing": []
        },
        "58780": {
            "id": "58780",
            "type": "E20 Biological Object",
            "short_type": "E20",
            "virtual": false,
            "text": "tiere",
            "search_string": "tiere",
            "begin": 5460,
            "end": 5465,
            "page": 130,
            "original_page": 0,
            "url": "",
            "citation": "",
            "line": 1,
            "txt_id": "Zoo_1914",
            "line_idx": 126,
            "institution": "Zoologisches Institut und zoologische Sammlung",
            "year": 1914,
            "mentions": 1,
            "color": "#5a50c4aa",
            "incoming": [
                "72812"
            ],
            "outgoing": [
                "72810",
                "72811"
            ]
        }
    },
    "Properties": {
        "72798": {
            "id": "72798",
            "type": "P22 transferred title to",
            "short_type": "P22",
            "source": "58763",
            "target": "58762"
        },
        "72799": {
            "id": "72799",
            "type": "P43 has dimension",
            "short_type": "P43",
            "source": "58763",
            "target": "58764"
        },
        "72800": {
            "id": "72800",
            "type": "P22 transferred title to",
            "short_type": "P22",
            "source": "58766",
            "target": "58765"
        },
        "72801": {
            "id": "72801",
            "type": "P22 transferred title to",
            "short_type": "P22",
            "source": "58772",
            "target": "58765"
        },
        "72802": {
            "id": "72802",
            "type": "P43 has dimension",
            "short_type": "P43",
            "source": "58768",
            "target": "58767"
        },
        "72803": {
            "id": "72803",
            "type": "P24 transferred title of",
            "short_type": "P24",
            "source": "58766",
            "target": "58768"
        },
        "72804": {
            "id": "72804",
            "type": "P23 transferred title from",
            "short_type": "P23",
            "source": "58772",
            "target": "58769"
        },
        "72805": {
            "id": "72805",
            "type": "P53 has former or current location",
            "short_type": "P53",
            "source": "58769",
            "target": "58770"
        },
        "72806": {
            "id": "72806",
            "type": "P23 transferred title from",
            "short_type": "P23",
            "source": "58772",
            "target": "58771"
        },
        "72807": {
            "id": "72807",
            "type": "P44 has condition",
            "short_type": "P44",
            "source": "58774",
            "target": "58773"
        },
        "72808": {
            "id": "72808",
            "type": "P23 transferred title from",
            "short_type": "P23",
            "source": "58772",
            "target": "58774"
        },
        "72809": {
            "id": "72809",
            "type": "P53 has former or current location",
            "short_type": "P53",
            "source": "58774",
            "target": "58775"
        },
        "72810": {
            "id": "72810",
            "type": "P43 has dimension",
            "short_type": "P43",
            "source": "58780",
            "target": "58777"
        },
        "72811": {
            "id": "72811",
            "type": "P130 shows features of",
            "short_type": "P130",
            "source": "58780",
            "target": "58778"
        },
        "72812": {
            "id": "72812",
            "type": "P24 transferred title of",
            "short_type": "P24",
            "source": "58776",
            "target": "58780"
        },
        "72813": {
            "id": "72813",
            "type": "P43 has dimension",
            "short_type": "P43",
            "source": "58784",
            "target": "58781"
        },
        "72814": {
            "id": "72814",
            "type": "P130 shows features of",
            "short_type": "P130",
            "source": "58784",
            "target": "58782"
        },
        "72815": {
            "id": "72815",
            "type": "P24 transferred title of",
            "short_type": "P24",
            "source": "58776",
            "target": "58784"
        },
        "72816": {
            "id": "72816",
            "type": "P130 shows features of",
            "short_type": "P130",
            "source": "58784",
            "target": "58785"
        },
        "72817": {
            "id": "72817",
            "type": "P44 has condition",
            "short_type": "P44",
            "source": "58774",
            "target": "58787"
        },
        "72818": {
            "id": "72818",
            "type": "P23 transferred title from",
            "short_type": "P23",
            "source": "58790",
            "target": "58774"
        },
        "72819": {
            "id": "72819",
            "type": "P53 has former or current location",
            "short_type": "P53",
            "source": "58774",
            "target": "58775"
        },
        "72820": {
            "id": "72820",
            "type": "P130 shows features of",
            "short_type": "P130",
            "source": "58794",
            "target": "58791"
        },
        "72821": {
            "id": "72821",
            "type": "P43 has dimension",
            "short_type": "P43",
            "source": "58794",
            "target": "58793"
        },
        "72822": {
            "id": "72822",
            "type": "P24 transferred title of",
            "short_type": "P24",
            "source": "58790",
            "target": "58794"
        },
        "72823": {
            "id": "72823",
            "type": "P43 has dimension",
            "short_type": "P43",
            "source": "58796",
            "target": "58795"
        },
        "72824": {
            "id": "72824",
            "type": "P130 shows features of",
            "short_type": "P130",
            "source": "58794",
            "target": "58796"
        },
        "72825": {
            "id": "72825",
            "type": "P53 has former or current location",
            "short_type": "P53",
            "source": "58794",
            "target": "58797"
        },
        "72792": {
            "id": "72792",
            "type": "P2 has type",
            "short_type": "P2",
            "source": "58778",
            "target": "58779"
        },
        "72793": {
            "id": "72793",
            "type": "P2 has type",
            "short_type": "P2",
            "source": "58782",
            "target": "58779"
        },
        "72794": {
            "id": "72794",
            "type": "P2 has type",
            "short_type": "P2",
            "source": "58785",
            "target": "58779"
        },
        "72795": {
            "id": "72795",
            "type": "P2 has type",
            "short_type": "P2",
            "source": "58791",
            "target": "58779"
        },
        "72796": {
            "id": "72796",
            "type": "P22 transferred title to",
            "short_type": "P22",
            "source": "58776",
            "target": "58762"
        },
        "72797": {
            "id": "72797",
            "type": "P22 transferred title to",
            "short_type": "P22",
            "source": "58790",
            "target": "58762"
        },
        "72826": {
            "id": "72826",
            "type": "P2 has type",
            "short_type": "P2",
            "source": "58763",
            "target": "58798"
        },
        "72827": {
            "id": "72827",
            "type": "P2 has type",
            "short_type": "P2",
            "source": "58766",
            "target": "58798"
        },
        "72828": {
            "id": "72828",
            "type": "P2 has type",
            "short_type": "P2",
            "source": "58772",
            "target": "58798"
        },
        "72829": {
            "id": "72829",
            "type": "P2 has type",
            "short_type": "P2",
            "source": "58776",
            "target": "58798"
        },
        "72830": {
            "id": "72830",
            "type": "P2 has type",
            "short_type": "P2",
            "source": "58790",
            "target": "58798"
        },
        "72831": {
            "id": "72831",
            "type": "P2 has type",
            "short_type": "P2",
            "source": "58796",
            "target": "58779"
        }
    }
}